{
  "ln_from_fr": true,
  "meta": {
    "sw": {
      "name": "Sheria",
      "title": "Sheria za Chicken Road: Jinsi ya Kucheza kwa Usalama",
      "description": "Sheria na kanuni za Chicken Road: ugumu, Cash Out, RTP na tabia salama ya mchezo kwenye PowerBall Jackpot."
    },
    "ln": {
      "name": "Mibeko",
      "title": "Mibeko ya Chicken Road: Kobeta na Libateli",
      "description": "Mibeko mpe ba règles ya Chicken Road: difficulty, Cash Out, RTP mpe comportement ya solo mpo na kobeta malamu."
    }
  }
}
